.DS_Store
mobiledna/.DS_Store
mobiledna/__init__.py
mobiledna/advanced/__init__.py
mobiledna/advanced/data_mining.py
mobiledna/advanced/get_active_users.py
mobiledna/advanced/where_is_home.py
mobiledna/cache/app_meta.npy
mobiledna/communication/__init__.py
mobiledna/communication/elastic.py
mobiledna/communication/snapshot_restore.py
mobiledna/core/__init__.py
mobiledna/core/annotate.py
mobiledna/core/appevents.py
mobiledna/core/connectivity.py
mobiledna/core/features.py
mobiledna/core/help.py
mobiledna/core/notifications.py
mobiledna/core/sessions.py
mobiledna-0.8.1.dist-info/LICENSE
mobiledna-0.8.1.dist-info/METADATA
mobiledna-0.8.1.dist-info/WHEEL
mobiledna-0.8.1.dist-info/top_level.txt
mobiledna-0.8.1.dist-info/RECORD
