Metadata-Version: 2.1
Name: mobiledna
Version: 0.8.1
Summary: Codebase in support of mobileDNA platform
Home-page: https://github.ugent.be/imec-mict-UGent/mobiledna_py
Author: Kyle Van Gaeveren, Wouter Durnez & Simon Perneel
Author-email: Simon.Perneel@UGent.be
License: MIT
Classifier: Programming Language :: Python :: 3
Classifier: License :: OSI Approved :: MIT License
Classifier: Operating System :: OS Independent
License-File: LICENSE
Requires-Dist: numpy
Requires-Dist: pandas
Requires-Dist: tqdm
Requires-Dist: matplotlib
Requires-Dist: elasticsearch <=6.3.1
Requires-Dist: holidays
Requires-Dist: bs4
